<?xml version="1.0" encoding="utf-8"?>
<sketch id="49f44def-3e02-4492-a161-e220e4bede38">
  <point x="1116" y="1516" pressure="127" time="1158133685427" name="point" id="c6ea3893-dc2a-4038-959f-adacc745cb0b" />
  <point x="1116" y="1516" pressure="127" time="1158133685435" name="point" id="7f30fcf7-06fd-45bf-b5ab-9c79a7164e5f" />
  <point x="1116" y="1516" pressure="127" time="1158133685442" name="point" id="9e72333b-77db-409d-a8a1-25da0ab83a38" />
  <point x="1116" y="1516" pressure="127" time="1158133685450" name="point" id="5d733611-11f0-4ae0-a25f-1ea075e2ff4c" />
  <point x="1116" y="1516" pressure="127" time="1158133685457" name="point" id="426374c6-6053-4f7c-8a18-8a64463d9309" />
  <point x="1116" y="1516" pressure="127" time="1158133685465" name="point" id="a19edd21-8713-4d00-bcad-98cc72dad00e" />
  <point x="1120" y="1514" pressure="127" time="1158133685472" name="point" id="98320293-5e4d-4a13-830a-4555e82ceb62" />
  <point x="1123" y="1514" pressure="127" time="1158133685480" name="point" id="7c4ebb0c-8094-4825-9ec8-503b0fb05b28" />
  <point x="1126" y="1513" pressure="127" time="1158133685487" name="point" id="92c6cd92-266f-4483-ae0f-18ce238c74ad" />
  <point x="1130" y="1513" pressure="127" time="1158133685495" name="point" id="ee37c732-14b2-4822-8966-ea28aaa5aae0" />
  <point x="1135" y="1513" pressure="127" time="1158133685502" name="point" id="162f5305-9453-45f2-8787-5511706c496a" />
  <point x="1141" y="1513" pressure="127" time="1158133685510" name="point" id="5f7a9c4d-f412-4925-9198-14d31d0c60dc" />
  <point x="1146" y="1511" pressure="127" time="1158133685517" name="point" id="b2a906bc-f4cc-41e5-8007-cb5e809a6b50" />
  <point x="1153" y="1511" pressure="127" time="1158133685525" name="point" id="dd5272c8-a08d-49c6-a5ec-18a47d23804d" />
  <point x="1160" y="1509" pressure="127" time="1158133685532" name="point" id="24f8e033-4423-4895-b0cf-4b71c4289fa6" />
  <point x="1167" y="1508" pressure="127" time="1158133685540" name="point" id="10b09a85-2197-4e5e-9a86-9ced949754ef" />
  <point x="1174" y="1506" pressure="127" time="1158133685547" name="point" id="340276b8-21c0-4455-b848-64e5c5facd84" />
  <point x="1181" y="1505" pressure="127" time="1158133685555" name="point" id="18f20a2e-c3b1-4242-8833-35594f1b81cf" />
  <point x="1186" y="1503" pressure="127" time="1158133685563" name="point" id="eb7d1de0-5b59-4a8a-a9e7-83714a466282" />
  <point x="1192" y="1502" pressure="127" time="1158133685570" name="point" id="1bc08eea-739c-4fa3-943f-0591be0a3d74" />
  <point x="1196" y="1501" pressure="127" time="1158133685578" name="point" id="4492901d-8803-47ae-a541-5d047e287045" />
  <point x="1200" y="1500" pressure="127" time="1158133685585" name="point" id="345c21c0-bba2-4855-9b9e-290810130b15" />
  <point x="1203" y="1499" pressure="127" time="1158133685593" name="point" id="e5562f27-8039-4c93-ac5b-fdac0ffa48e2" />
  <point x="1203" y="1499" pressure="127" time="1158133685600" name="point" id="346fc786-6ba3-4405-8b61-e174ee0249f4" />
  <point x="1206" y="1499" pressure="127" time="1158133685608" name="point" id="41ebc873-3747-4c7d-971c-6787f3586685" />
  <point x="1206" y="1499" pressure="127" time="1158133685615" name="point" id="2f02ce2c-d86d-4648-b7cc-32e6ab8f6fbb" />
  <point x="1209" y="1501" pressure="127" time="1158133685623" name="point" id="e1ec610e-62ee-4479-a5ab-0e93edad32cf" />
  <point x="1209" y="1501" pressure="127" time="1158133685630" name="point" id="478dfe79-6849-4312-b249-bbb18b827446" />
  <point x="1209" y="1501" pressure="127" time="1158133685638" name="point" id="25e94571-2482-49b1-a1a6-6f4cfbdfee19" />
  <point x="1212" y="1504" pressure="127" time="1158133685645" name="point" id="3a0d1d84-88f3-4075-ba01-81915ad57e44" />
  <point x="1212" y="1504" pressure="127" time="1158133685653" name="point" id="ee6a249a-47fb-41c8-b2d9-4c34cb436c05" />
  <point x="1212" y="1506" pressure="127" time="1158133685660" name="point" id="aa76a94e-7bdb-4fed-824b-dd64bdaaf26d" />
  <point x="1212" y="1506" pressure="127" time="1158133685668" name="point" id="353d0024-a623-47cf-8011-a81f1b320894" />
  <point x="1212" y="1509" pressure="127" time="1158133685675" name="point" id="5422837c-1054-4e4e-acb9-9bf08ce15544" />
  <point x="1212" y="1509" pressure="127" time="1158133685683" name="point" id="ee1c5087-f4ba-402e-a33c-0ae9fe6c5740" />
  <point x="1212" y="1512" pressure="127" time="1158133685690" name="point" id="9c894f24-1c48-4ece-89ff-a48ea46624d3" />
  <point x="1212" y="1512" pressure="127" time="1158133685698" name="point" id="0cd8ce31-bd9a-48c3-9150-4f15280d4f98" />
  <point x="1211" y="1515" pressure="127" time="1158133685705" name="point" id="4172f47b-aba1-4e7a-a4b6-bc7edb797986" />
  <point x="1210" y="1517" pressure="127" time="1158133685713" name="point" id="dcaa283a-bdbe-4b08-a2df-f062390b82cc" />
  <point x="1209" y="1521" pressure="127" time="1158133685720" name="point" id="bb287dc4-fc50-48b9-a1c1-2c9d254353e7" />
  <point x="1208" y="1523" pressure="127" time="1158133685728" name="point" id="a2e7be2f-684d-4fb6-a6f5-b674b13034ac" />
  <point x="1206" y="1528" pressure="127" time="1158133685735" name="point" id="17fd330c-fefd-41cb-b5ba-0add29d51f55" />
  <point x="1204" y="1532" pressure="127" time="1158133685743" name="point" id="033f2468-d8eb-4ce9-a42d-5937a7ab9a03" />
  <point x="1202" y="1538" pressure="127" time="1158133685750" name="point" id="3e7d4bd9-a26d-43d1-8297-df966777564a" />
  <point x="1200" y="1545" pressure="127" time="1158133685758" name="point" id="7e1e7d62-bb50-446c-9c84-9f22638ed0b6" />
  <point x="1198" y="1551" pressure="127" time="1158133685766" name="point" id="65d9b9c9-92ec-477c-a15b-d4a1db4497c3" />
  <point x="1195" y="1558" pressure="127" time="1158133685773" name="point" id="deaa1f32-5862-43bc-a48d-ad4c8d7087d5" />
  <point x="1193" y="1566" pressure="127" time="1158133685781" name="point" id="d34f7165-92cd-4616-a77d-eaf95465d792" />
  <point x="1190" y="1574" pressure="127" time="1158133685788" name="point" id="c7d09777-6b43-426f-97cb-fc16b67a68d7" />
  <point x="1188" y="1583" pressure="127" time="1158133685796" name="point" id="7e8619c7-1860-44c8-b133-e4fb0cace4ba" />
  <point x="1186" y="1591" pressure="127" time="1158133685803" name="point" id="3b0a8d44-728d-40d4-ad37-8b6cd502608e" />
  <point x="1183" y="1600" pressure="127" time="1158133685811" name="point" id="ab038298-c7ea-477f-9302-051351d400ab" />
  <point x="1180" y="1608" pressure="127" time="1158133685818" name="point" id="53ae5bed-c976-4ce7-a2ee-9b0390ca37e7" />
  <point x="1177" y="1616" pressure="127" time="1158133685826" name="point" id="6dfbbb4f-75e3-431a-98cd-86d56c43fe8b" />
  <point x="1176" y="1623" pressure="127" time="1158133685833" name="point" id="a375ee59-f306-4bb6-950a-9f71b1e27cdc" />
  <point x="1174" y="1629" pressure="127" time="1158133685841" name="point" id="26b4c5b7-4eb9-4e28-9bf6-92c808aa4ce8" />
  <point x="1172" y="1635" pressure="127" time="1158133685848" name="point" id="6a0ed158-405c-4be9-8080-be1cfa264917" />
  <point x="1170" y="1640" pressure="127" time="1158133685856" name="point" id="97b829ac-1b8f-4e52-ae97-2c534d1d4ade" />
  <point x="1169" y="1644" pressure="127" time="1158133685863" name="point" id="167fefdc-a5ba-42ab-bd6c-2f2fd81296b7" />
  <point x="1168" y="1645" pressure="127" time="1158133685871" name="point" id="00ba62bb-1643-4e7c-b9ee-b6e9819c3e8c" />
  <point x="1168" y="1645" pressure="127" time="1158133685878" name="point" id="3b48fb62-52ef-4386-8d32-0c0d916501ef" />
  <point x="1166" y="1648" pressure="127" time="1158133685886" name="point" id="7b3b40f6-3f47-4e6c-9957-e43b1ba46498" />
  <point x="1166" y="1648" pressure="127" time="1158133685893" name="point" id="875e28a6-5c7f-41a1-8e7c-311d362c858c" />
  <point x="1166" y="1648" pressure="127" time="1158133685901" name="point" id="e43cb9b2-ee87-474e-80de-83c2be7d7e6f" />
  <point x="1162" y="1648" pressure="127" time="1158133685908" name="point" id="8b0311cc-3812-4572-9d47-9b70151ff7a8" />
  <point x="1162" y="1648" pressure="127" time="1158133685916" name="point" id="873d03ce-e6ae-4ea5-bb39-4cc2c1c2efe0" />
  <point x="1159" y="1646" pressure="127" time="1158133685923" name="point" id="28bbf4dc-530f-4ecf-a7e4-6ca20e2351a5" />
  <point x="1159" y="1646" pressure="127" time="1158133685931" name="point" id="bee7c8d7-7f0c-47a4-8fd1-0db702a533cf" />
  <point x="1155" y="1642" pressure="127" time="1158133685938" name="point" id="8d8d4cad-4e78-4852-91c6-39a6b1e09344" />
  <point x="1153" y="1640" pressure="127" time="1158133685946" name="point" id="302e0b5b-2497-4a77-bf0e-3ca671868cb9" />
  <point x="1151" y="1637" pressure="127" time="1158133685953" name="point" id="c42493d9-f425-4cd2-8b7b-c20dbaabf5bf" />
  <point x="1149" y="1633" pressure="127" time="1158133685961" name="point" id="c7744a67-e1a8-4127-a5df-13ee51b70363" />
  <point x="1146" y="1629" pressure="127" time="1158133685969" name="point" id="2deacdd6-1eb6-4ea4-99a6-2521f27f51fc" />
  <point x="1143" y="1625" pressure="127" time="1158133685976" name="point" id="b99d8284-81d5-4c0e-a6ae-4b8d45750234" />
  <point x="1140" y="1619" pressure="127" time="1158133685984" name="point" id="583a4442-5d88-4670-a0fc-29b11b2c0eac" />
  <point x="1136" y="1614" pressure="127" time="1158133685991" name="point" id="84ff7b43-1fd9-4cf5-aae9-ac891508212a" />
  <point x="1133" y="1608" pressure="127" time="1158133685999" name="point" id="ac3d6864-5d59-4a46-8e37-ef1f03f023f3" />
  <point x="1131" y="1600" pressure="127" time="1158133686006" name="point" id="bcc9b05b-c69b-40f0-b6db-1762480c4774" />
  <point x="1127" y="1590" pressure="127" time="1158133686014" name="point" id="47774c05-6b41-4e21-8647-9a4910d20836" />
  <point x="1124" y="1580" pressure="127" time="1158133686021" name="point" id="d39bce60-2c78-4fc2-af1d-41486188c0d5" />
  <point x="1121" y="1570" pressure="127" time="1158133686029" name="point" id="6510b4ef-7a0e-4d12-9adc-ad19e182e420" />
  <point x="1118" y="1559" pressure="127" time="1158133686036" name="point" id="6fe287b5-5c7b-413d-a847-a9543594fce2" />
  <point x="1116" y="1548" pressure="127" time="1158133686044" name="point" id="49ea1ab1-6ac9-4cfb-bfa0-2d5009183e31" />
  <point x="1113" y="1537" pressure="127" time="1158133686051" name="point" id="6eb6d6fe-0f60-47a5-a114-4b057c3cef8d" />
  <point x="1110" y="1528" pressure="127" time="1158133686059" name="point" id="57e70a99-cadc-4e17-84ff-f62f8572e7ea" />
  <point x="1108" y="1521" pressure="127" time="1158133686066" name="point" id="37527de6-3647-4355-83e1-bb4bb98d90ae" />
  <point x="1107" y="1514" pressure="127" time="1158133686074" name="point" id="3551e645-dca2-4268-bfaa-4c97b5516306" />
  <point x="1107" y="1511" pressure="127" time="1158133686081" name="point" id="9e97aef6-9e02-4bdc-8e97-364fe1bbee0c" />
  <point x="1106" y="1508" pressure="127" time="1158133686089" name="point" id="191a914a-8837-4c55-9caa-b833497cfb49" />
  <point x="1106" y="1508" pressure="127" time="1158133686096" name="point" id="7e103fb6-95a0-4162-b4af-f8ed988ce741" />
  <point x="1105" y="1505" pressure="127" time="1158133686104" name="point" id="5aae1bf2-6a7a-427f-bbca-cb434e8b3dce" />
  <point x="1105" y="1505" pressure="127" time="1158133686111" name="point" id="0bee3a70-660d-419c-9225-fdc474e04b40" />
  <point x="1107" y="1506" pressure="127" time="1158133686119" name="point" id="be32a140-a00c-4cb1-9131-7f1d3b4bfa55" />
  <point x="1107" y="1506" pressure="127" time="1158133686126" name="point" id="90a20ae1-cdd4-404f-8bdd-6a5a5c77e372" />
  <point x="1107" y="1506" pressure="127" time="1158133686134" name="point" id="c38ae6d1-0f50-42d9-9f6a-091c4dcb54d4" />
  <point x="1109" y="1509" pressure="127" time="1158133686141" name="point" id="aa6215d8-8395-4feb-a6ca-abdb7c70ebef" />
  <point x="1109" y="1509" pressure="127" time="1158133686149" name="point" id="5e9f3427-12ee-4c93-9924-2e2446036c80" />
  <point x="1172" y="1652" pressure="127" time="1158133686467" name="point" id="b786503d-e1d6-44ee-9e1f-4d5e6ae49388" />
  <point x="1172" y="1652" pressure="127" time="1158133686474" name="point" id="e324e7b8-c48f-4ed1-b086-0d905011fa73" />
  <point x="1170" y="1652" pressure="127" time="1158133686482" name="point" id="c67a947c-afe3-468a-9073-0be44bff0c9c" />
  <point x="1170" y="1652" pressure="127" time="1158133686489" name="point" id="a8e03e4d-b655-4e58-a224-7420d3a9ce7e" />
  <point x="1170" y="1649" pressure="127" time="1158133686497" name="point" id="99d0937c-f83b-4590-9d82-aafabfdc1575" />
  <point x="1170" y="1649" pressure="127" time="1158133686504" name="point" id="5bb19d1a-0433-40a5-9eb5-35ff5db6ea18" />
  <point x="1168" y="1647" pressure="127" time="1158133686512" name="point" id="0c7d5eda-44d7-4a87-952e-00eebcf8e41f" />
  <point x="1165" y="1647" pressure="127" time="1158133686519" name="point" id="29f5fa31-d5db-4367-b522-ffb590340442" />
  <point x="1165" y="1647" pressure="127" time="1158133686527" name="point" id="215005f4-83eb-403b-8936-9cbf171ffb5f" />
  <point x="1161" y="1647" pressure="127" time="1158133686534" name="point" id="dbc4a4d8-c914-401b-9ab3-f0af24f69018" />
  <point x="1159" y="1647" pressure="127" time="1158133686542" name="point" id="331af2a4-cb85-4971-95bd-2a0ec6753e54" />
  <point x="1155" y="1648" pressure="127" time="1158133686549" name="point" id="09785004-ac16-4984-8431-650e254cf55c" />
  <point x="1152" y="1650" pressure="127" time="1158133686557" name="point" id="90664721-1f8d-4fd4-a619-f80269f91d74" />
  <point x="1149" y="1652" pressure="127" time="1158133686564" name="point" id="fb681965-7909-4c90-85f5-031638dffc04" />
  <point x="1146" y="1653" pressure="127" time="1158133686572" name="point" id="52c689d3-72e1-40ba-991c-cfdb8218a848" />
  <point x="1143" y="1657" pressure="127" time="1158133686579" name="point" id="6d8ea796-0911-45e5-bd5c-94490dd3e60a" />
  <point x="1142" y="1660" pressure="127" time="1158133686587" name="point" id="c0d9e079-096c-4731-b653-191bb2c674a9" />
  <point x="1140" y="1665" pressure="127" time="1158133686594" name="point" id="4fba46f9-0977-46fe-a764-826fb29ff192" />
  <point x="1139" y="1669" pressure="127" time="1158133686602" name="point" id="1638b0ee-1683-4a8a-8325-93a07aec5b3d" />
  <point x="1138" y="1676" pressure="127" time="1158133686609" name="point" id="19a48336-9f58-422c-8fee-a86ef4c1c4e9" />
  <point x="1138" y="1681" pressure="127" time="1158133686617" name="point" id="22af4cd6-116a-41f7-8360-af3b946971ac" />
  <point x="1138" y="1687" pressure="127" time="1158133686625" name="point" id="7a9a77bf-b8a0-4421-b50c-c699e70dafd4" />
  <point x="1140" y="1693" pressure="127" time="1158133686632" name="point" id="ebe31ad6-b0a8-4acf-bd18-2b23d1793791" />
  <point x="1142" y="1700" pressure="127" time="1158133686640" name="point" id="e1357c93-c4dd-4356-b930-750f1e1e0042" />
  <point x="1144" y="1705" pressure="127" time="1158133686647" name="point" id="66cf52d2-3a4a-4f13-9ec7-884cec1d65e9" />
  <point x="1148" y="1709" pressure="127" time="1158133686655" name="point" id="61ae2d0c-e227-44b8-8598-99a518491f5d" />
  <point x="1151" y="1713" pressure="127" time="1158133686662" name="point" id="82359605-a706-4687-94fe-84763693f305" />
  <point x="1157" y="1716" pressure="127" time="1158133686670" name="point" id="b3cdd621-f86f-4b6f-9edd-c470e2b20bfc" />
  <point x="1161" y="1717" pressure="127" time="1158133686677" name="point" id="b88d57a6-1a41-43ad-aff0-dc54800b6938" />
  <point x="1168" y="1717" pressure="127" time="1158133686685" name="point" id="061e1733-0981-419f-9902-5ace53381ee3" />
  <point x="1173" y="1715" pressure="127" time="1158133686692" name="point" id="275006e0-27fc-4886-b786-525e9ce71bf7" />
  <point x="1177" y="1712" pressure="127" time="1158133686700" name="point" id="74a70110-d6c5-4e2a-aae5-dae1b401dd56" />
  <point x="1183" y="1708" pressure="127" time="1158133686707" name="point" id="19775339-d88f-4268-aa45-a89275aac932" />
  <point x="1187" y="1702" pressure="127" time="1158133686715" name="point" id="bf9e7729-60e8-4c0d-a104-f8bb35e5a3ca" />
  <point x="1190" y="1697" pressure="127" time="1158133686722" name="point" id="77a7d992-9b4c-442e-8aab-d1c43c3341e7" />
  <point x="1192" y="1690" pressure="127" time="1158133686730" name="point" id="688b172e-1bba-45ff-ae7f-456333075a20" />
  <point x="1194" y="1684" pressure="127" time="1158133686737" name="point" id="ce87c079-db07-413b-9ac0-fa5a11233a71" />
  <point x="1195" y="1676" pressure="127" time="1158133686745" name="point" id="be476602-d6f5-4372-87c2-5442ac366a26" />
  <point x="1195" y="1670" pressure="127" time="1158133686752" name="point" id="9bb6303f-1aa1-4f1c-ac21-fa911f139368" />
  <point x="1195" y="1664" pressure="127" time="1158133686760" name="point" id="9903871d-ac58-4993-8770-3b28d4802374" />
  <point x="1193" y="1660" pressure="127" time="1158133686767" name="point" id="ec0aebf0-d1df-43c8-a0be-8fc894bdc0b1" />
  <point x="1190" y="1654" pressure="127" time="1158133686775" name="point" id="2c8ee111-e2f9-49d1-abe0-ce21342011ce" />
  <point x="1188" y="1651" pressure="127" time="1158133686782" name="point" id="ae1ce196-c821-4fed-b037-e3f2de666544" />
  <point x="1185" y="1648" pressure="127" time="1158133686790" name="point" id="91710d11-ebcf-48ff-b71b-c12092f5ca1a" />
  <point x="1183" y="1645" pressure="127" time="1158133686797" name="point" id="8b37e1f6-e7b7-4c14-9ec3-88afc1eb1c66" />
  <point x="1179" y="1644" pressure="127" time="1158133686805" name="point" id="9330e106-0f28-4b2a-a7ae-91b523282c13" />
  <shape type="substroke" name="substroke" id="0ad8cd7f-ca31-4823-ba6d-689d7df564d2" time="1158133685630" x="1116" y="1499" color="-37009" height="17" width="93" penTip="Ball" penWidth="15" penHeight="15" raster="CopyPen" start="c6ea3893-dc2a-4038-959f-adacc745cb0b" end="478dfe79-6849-4312-b249-bbb18b827446" source="ConverterJnt">
    <arg type="point">c6ea3893-dc2a-4038-959f-adacc745cb0b</arg>
    <arg type="point">7f30fcf7-06fd-45bf-b5ab-9c79a7164e5f</arg>
    <arg type="point">9e72333b-77db-409d-a8a1-25da0ab83a38</arg>
    <arg type="point">5d733611-11f0-4ae0-a25f-1ea075e2ff4c</arg>
    <arg type="point">426374c6-6053-4f7c-8a18-8a64463d9309</arg>
    <arg type="point">a19edd21-8713-4d00-bcad-98cc72dad00e</arg>
    <arg type="point">98320293-5e4d-4a13-830a-4555e82ceb62</arg>
    <arg type="point">7c4ebb0c-8094-4825-9ec8-503b0fb05b28</arg>
    <arg type="point">92c6cd92-266f-4483-ae0f-18ce238c74ad</arg>
    <arg type="point">ee37c732-14b2-4822-8966-ea28aaa5aae0</arg>
    <arg type="point">162f5305-9453-45f2-8787-5511706c496a</arg>
    <arg type="point">5f7a9c4d-f412-4925-9198-14d31d0c60dc</arg>
    <arg type="point">b2a906bc-f4cc-41e5-8007-cb5e809a6b50</arg>
    <arg type="point">dd5272c8-a08d-49c6-a5ec-18a47d23804d</arg>
    <arg type="point">24f8e033-4423-4895-b0cf-4b71c4289fa6</arg>
    <arg type="point">10b09a85-2197-4e5e-9a86-9ced949754ef</arg>
    <arg type="point">340276b8-21c0-4455-b848-64e5c5facd84</arg>
    <arg type="point">18f20a2e-c3b1-4242-8833-35594f1b81cf</arg>
    <arg type="point">eb7d1de0-5b59-4a8a-a9e7-83714a466282</arg>
    <arg type="point">1bc08eea-739c-4fa3-943f-0591be0a3d74</arg>
    <arg type="point">4492901d-8803-47ae-a541-5d047e287045</arg>
    <arg type="point">345c21c0-bba2-4855-9b9e-290810130b15</arg>
    <arg type="point">e5562f27-8039-4c93-ac5b-fdac0ffa48e2</arg>
    <arg type="point">346fc786-6ba3-4405-8b61-e174ee0249f4</arg>
    <arg type="point">41ebc873-3747-4c7d-971c-6787f3586685</arg>
    <arg type="point">2f02ce2c-d86d-4648-b7cc-32e6ab8f6fbb</arg>
    <arg type="point">e1ec610e-62ee-4479-a5ab-0e93edad32cf</arg>
    <arg type="point">478dfe79-6849-4312-b249-bbb18b827446</arg>
  </shape>
  <shape type="substroke" name="substroke" id="096ead91-abf5-4f06-87a1-6c03d3542b8f" time="1158133685893" x="1166" y="1501" color="-37009" height="147" width="46" penTip="Ball" penWidth="15" penHeight="15" raster="CopyPen" start="25e94571-2482-49b1-a1a6-6f4cfbdfee19" end="875e28a6-5c7f-41a1-8e7c-311d362c858c" source="ConverterJnt">
    <arg type="point">25e94571-2482-49b1-a1a6-6f4cfbdfee19</arg>
    <arg type="point">3a0d1d84-88f3-4075-ba01-81915ad57e44</arg>
    <arg type="point">ee6a249a-47fb-41c8-b2d9-4c34cb436c05</arg>
    <arg type="point">aa76a94e-7bdb-4fed-824b-dd64bdaaf26d</arg>
    <arg type="point">353d0024-a623-47cf-8011-a81f1b320894</arg>
    <arg type="point">5422837c-1054-4e4e-acb9-9bf08ce15544</arg>
    <arg type="point">ee1c5087-f4ba-402e-a33c-0ae9fe6c5740</arg>
    <arg type="point">9c894f24-1c48-4ece-89ff-a48ea46624d3</arg>
    <arg type="point">0cd8ce31-bd9a-48c3-9150-4f15280d4f98</arg>
    <arg type="point">4172f47b-aba1-4e7a-a4b6-bc7edb797986</arg>
    <arg type="point">dcaa283a-bdbe-4b08-a2df-f062390b82cc</arg>
    <arg type="point">bb287dc4-fc50-48b9-a1c1-2c9d254353e7</arg>
    <arg type="point">a2e7be2f-684d-4fb6-a6f5-b674b13034ac</arg>
    <arg type="point">17fd330c-fefd-41cb-b5ba-0add29d51f55</arg>
    <arg type="point">033f2468-d8eb-4ce9-a42d-5937a7ab9a03</arg>
    <arg type="point">3e7d4bd9-a26d-43d1-8297-df966777564a</arg>
    <arg type="point">7e1e7d62-bb50-446c-9c84-9f22638ed0b6</arg>
    <arg type="point">65d9b9c9-92ec-477c-a15b-d4a1db4497c3</arg>
    <arg type="point">deaa1f32-5862-43bc-a48d-ad4c8d7087d5</arg>
    <arg type="point">d34f7165-92cd-4616-a77d-eaf95465d792</arg>
    <arg type="point">c7d09777-6b43-426f-97cb-fc16b67a68d7</arg>
    <arg type="point">7e8619c7-1860-44c8-b133-e4fb0cace4ba</arg>
    <arg type="point">3b0a8d44-728d-40d4-ad37-8b6cd502608e</arg>
    <arg type="point">ab038298-c7ea-477f-9302-051351d400ab</arg>
    <arg type="point">53ae5bed-c976-4ce7-a2ee-9b0390ca37e7</arg>
    <arg type="point">6dfbbb4f-75e3-431a-98cd-86d56c43fe8b</arg>
    <arg type="point">a375ee59-f306-4bb6-950a-9f71b1e27cdc</arg>
    <arg type="point">26b4c5b7-4eb9-4e28-9bf6-92c808aa4ce8</arg>
    <arg type="point">6a0ed158-405c-4be9-8080-be1cfa264917</arg>
    <arg type="point">97b829ac-1b8f-4e52-ae97-2c534d1d4ade</arg>
    <arg type="point">167fefdc-a5ba-42ab-bd6c-2f2fd81296b7</arg>
    <arg type="point">00ba62bb-1643-4e7c-b9ee-b6e9819c3e8c</arg>
    <arg type="point">3b48fb62-52ef-4386-8d32-0c0d916501ef</arg>
    <arg type="point">7b3b40f6-3f47-4e6c-9957-e43b1ba46498</arg>
    <arg type="point">875e28a6-5c7f-41a1-8e7c-311d362c858c</arg>
  </shape>
  <shape type="substroke" name="substroke" id="fdf590c5-4ba1-4f61-8079-0eaf9a0a3b39" time="1158133686149" x="1105" y="1505" color="-37009" height="143" width="61" penTip="Ball" penWidth="15" penHeight="15" raster="CopyPen" start="e43cb9b2-ee87-474e-80de-83c2be7d7e6f" end="5e9f3427-12ee-4c93-9924-2e2446036c80" source="ConverterJnt">
    <arg type="point">e43cb9b2-ee87-474e-80de-83c2be7d7e6f</arg>
    <arg type="point">8b0311cc-3812-4572-9d47-9b70151ff7a8</arg>
    <arg type="point">873d03ce-e6ae-4ea5-bb39-4cc2c1c2efe0</arg>
    <arg type="point">28bbf4dc-530f-4ecf-a7e4-6ca20e2351a5</arg>
    <arg type="point">bee7c8d7-7f0c-47a4-8fd1-0db702a533cf</arg>
    <arg type="point">8d8d4cad-4e78-4852-91c6-39a6b1e09344</arg>
    <arg type="point">302e0b5b-2497-4a77-bf0e-3ca671868cb9</arg>
    <arg type="point">c42493d9-f425-4cd2-8b7b-c20dbaabf5bf</arg>
    <arg type="point">c7744a67-e1a8-4127-a5df-13ee51b70363</arg>
    <arg type="point">2deacdd6-1eb6-4ea4-99a6-2521f27f51fc</arg>
    <arg type="point">b99d8284-81d5-4c0e-a6ae-4b8d45750234</arg>
    <arg type="point">583a4442-5d88-4670-a0fc-29b11b2c0eac</arg>
    <arg type="point">84ff7b43-1fd9-4cf5-aae9-ac891508212a</arg>
    <arg type="point">ac3d6864-5d59-4a46-8e37-ef1f03f023f3</arg>
    <arg type="point">bcc9b05b-c69b-40f0-b6db-1762480c4774</arg>
    <arg type="point">47774c05-6b41-4e21-8647-9a4910d20836</arg>
    <arg type="point">d39bce60-2c78-4fc2-af1d-41486188c0d5</arg>
    <arg type="point">6510b4ef-7a0e-4d12-9adc-ad19e182e420</arg>
    <arg type="point">6fe287b5-5c7b-413d-a847-a9543594fce2</arg>
    <arg type="point">49ea1ab1-6ac9-4cfb-bfa0-2d5009183e31</arg>
    <arg type="point">6eb6d6fe-0f60-47a5-a114-4b057c3cef8d</arg>
    <arg type="point">57e70a99-cadc-4e17-84ff-f62f8572e7ea</arg>
    <arg type="point">37527de6-3647-4355-83e1-bb4bb98d90ae</arg>
    <arg type="point">3551e645-dca2-4268-bfaa-4c97b5516306</arg>
    <arg type="point">9e97aef6-9e02-4bdc-8e97-364fe1bbee0c</arg>
    <arg type="point">191a914a-8837-4c55-9caa-b833497cfb49</arg>
    <arg type="point">7e103fb6-95a0-4162-b4af-f8ed988ce741</arg>
    <arg type="point">5aae1bf2-6a7a-427f-bbca-cb434e8b3dce</arg>
    <arg type="point">0bee3a70-660d-419c-9225-fdc474e04b40</arg>
    <arg type="point">be32a140-a00c-4cb1-9131-7f1d3b4bfa55</arg>
    <arg type="point">90a20ae1-cdd4-404f-8bdd-6a5a5c77e372</arg>
    <arg type="point">c38ae6d1-0f50-42d9-9f6a-091c4dcb54d4</arg>
    <arg type="point">aa6215d8-8395-4feb-a6ca-abdb7c70ebef</arg>
    <arg type="point">5e9f3427-12ee-4c93-9924-2e2446036c80</arg>
  </shape>
  <shape type="substroke" name="substroke" id="ecca4541-985f-42d6-a4d3-c5219aff5f76" time="1158133686812" x="1138" y="1644" color="-37009" height="73" width="57" penTip="Ball" penWidth="15" penHeight="15" raster="CopyPen" start="b786503d-e1d6-44ee-9e1f-4d5e6ae49388" end="9330e106-0f28-4b2a-a7ae-91b523282c13" source="ConverterJnt">
    <arg type="point">b786503d-e1d6-44ee-9e1f-4d5e6ae49388</arg>
    <arg type="point">e324e7b8-c48f-4ed1-b086-0d905011fa73</arg>
    <arg type="point">c67a947c-afe3-468a-9073-0be44bff0c9c</arg>
    <arg type="point">a8e03e4d-b655-4e58-a224-7420d3a9ce7e</arg>
    <arg type="point">99d0937c-f83b-4590-9d82-aafabfdc1575</arg>
    <arg type="point">5bb19d1a-0433-40a5-9eb5-35ff5db6ea18</arg>
    <arg type="point">0c7d5eda-44d7-4a87-952e-00eebcf8e41f</arg>
    <arg type="point">29f5fa31-d5db-4367-b522-ffb590340442</arg>
    <arg type="point">215005f4-83eb-403b-8936-9cbf171ffb5f</arg>
    <arg type="point">dbc4a4d8-c914-401b-9ab3-f0af24f69018</arg>
    <arg type="point">331af2a4-cb85-4971-95bd-2a0ec6753e54</arg>
    <arg type="point">09785004-ac16-4984-8431-650e254cf55c</arg>
    <arg type="point">90664721-1f8d-4fd4-a619-f80269f91d74</arg>
    <arg type="point">fb681965-7909-4c90-85f5-031638dffc04</arg>
    <arg type="point">52c689d3-72e1-40ba-991c-cfdb8218a848</arg>
    <arg type="point">6d8ea796-0911-45e5-bd5c-94490dd3e60a</arg>
    <arg type="point">c0d9e079-096c-4731-b653-191bb2c674a9</arg>
    <arg type="point">4fba46f9-0977-46fe-a764-826fb29ff192</arg>
    <arg type="point">1638b0ee-1683-4a8a-8325-93a07aec5b3d</arg>
    <arg type="point">19a48336-9f58-422c-8fee-a86ef4c1c4e9</arg>
    <arg type="point">22af4cd6-116a-41f7-8360-af3b946971ac</arg>
    <arg type="point">7a9a77bf-b8a0-4421-b50c-c699e70dafd4</arg>
    <arg type="point">ebe31ad6-b0a8-4acf-bd18-2b23d1793791</arg>
    <arg type="point">e1357c93-c4dd-4356-b930-750f1e1e0042</arg>
    <arg type="point">66cf52d2-3a4a-4f13-9ec7-884cec1d65e9</arg>
    <arg type="point">61ae2d0c-e227-44b8-8598-99a518491f5d</arg>
    <arg type="point">82359605-a706-4687-94fe-84763693f305</arg>
    <arg type="point">b3cdd621-f86f-4b6f-9edd-c470e2b20bfc</arg>
    <arg type="point">b88d57a6-1a41-43ad-aff0-dc54800b6938</arg>
    <arg type="point">061e1733-0981-419f-9902-5ace53381ee3</arg>
    <arg type="point">275006e0-27fc-4886-b786-525e9ce71bf7</arg>
    <arg type="point">74a70110-d6c5-4e2a-aae5-dae1b401dd56</arg>
    <arg type="point">19775339-d88f-4268-aa45-a89275aac932</arg>
    <arg type="point">bf9e7729-60e8-4c0d-a104-f8bb35e5a3ca</arg>
    <arg type="point">77a7d992-9b4c-442e-8aab-d1c43c3341e7</arg>
    <arg type="point">688b172e-1bba-45ff-ae7f-456333075a20</arg>
    <arg type="point">ce87c079-db07-413b-9ac0-fa5a11233a71</arg>
    <arg type="point">be476602-d6f5-4372-87c2-5442ac366a26</arg>
    <arg type="point">9bb6303f-1aa1-4f1c-ac21-fa911f139368</arg>
    <arg type="point">9903871d-ac58-4993-8770-3b28d4802374</arg>
    <arg type="point">ec0aebf0-d1df-43c8-a0be-8fc894bdc0b1</arg>
    <arg type="point">2c8ee111-e2f9-49d1-abe0-ce21342011ce</arg>
    <arg type="point">ae1ce196-c821-4fed-b037-e3f2de666544</arg>
    <arg type="point">91710d11-ebcf-48ff-b71b-c12092f5ca1a</arg>
    <arg type="point">8b37e1f6-e7b7-4c14-9ec3-88afc1eb1c66</arg>
    <arg type="point">9330e106-0f28-4b2a-a7ae-91b523282c13</arg>
  </shape>
  <shape type="stroke" name="stroke" id="3db91a56-0a60-4dd9-99e0-ec9440b8ef2c" time="1158133685630" x="1116" y="1499" height="17" width="93" start="0ad8cd7f-ca31-4823-ba6d-689d7df564d2" end="0ad8cd7f-ca31-4823-ba6d-689d7df564d2">
    <arg type="substroke">0ad8cd7f-ca31-4823-ba6d-689d7df564d2</arg>
  </shape>
  <shape type="stroke" name="stroke" id="042fc201-02a9-47af-a334-a2f75c70e656" time="1158133685893" x="1166" y="1501" height="147" width="46" start="096ead91-abf5-4f06-87a1-6c03d3542b8f" end="096ead91-abf5-4f06-87a1-6c03d3542b8f">
    <arg type="substroke">096ead91-abf5-4f06-87a1-6c03d3542b8f</arg>
  </shape>
  <shape type="stroke" name="stroke" id="b2b4fed6-c3fe-4818-9f06-dd3612997382" time="1158133686149" x="1105" y="1505" height="143" width="61" start="fdf590c5-4ba1-4f61-8079-0eaf9a0a3b39" end="fdf590c5-4ba1-4f61-8079-0eaf9a0a3b39">
    <arg type="substroke">fdf590c5-4ba1-4f61-8079-0eaf9a0a3b39</arg>
  </shape>
  <shape type="stroke" name="stroke" id="7d3870e4-91cc-4b23-84cc-deaf597bc6d7" time="1158133686812" x="1138" y="1644" height="73" width="57" start="ecca4541-985f-42d6-a4d3-c5219aff5f76" end="ecca4541-985f-42d6-a4d3-c5219aff5f76">
    <arg type="substroke">ecca4541-985f-42d6-a4d3-c5219aff5f76</arg>
  </shape>
</sketch>